pathtmpl/__init__.py
pathtmpl/models.py
pathtmpl/template.py
pathtmpl-0.2.0.dist-info/LICENSE
pathtmpl-0.2.0.dist-info/METADATA
pathtmpl-0.2.0.dist-info/WHEEL
pathtmpl-0.2.0.dist-info/RECORD
