Metadata-Version: 2.1
Name: pathtmpl
Version: 0.2.0
Summary: Path Template
Author: Eugen Ciur
Author-email: eugen@papermerge.com
Requires-Python: >=3.13,<4.0
Classifier: Programming Language :: Python :: 3
Classifier: Programming Language :: Python :: 3.13
Requires-Dist: jinja2 (>=3.1.4,<4.0.0)
Requires-Dist: pydantic (>=2.9,<3.0)
